<annotation>
	<folder></folder>
	<filename>ck0lx9tk9g22n0838e6v5csum_jpeg.rf.11711fcadd74b41a401f81ee9c5ccfae.jpg</filename>
	<path>ck0lx9tk9g22n0838e6v5csum_jpeg.rf.11711fcadd74b41a401f81ee9c5ccfae.jpg</path>
	<source>
		<database>roboflow.ai</database>
	</source>
	<size>
		<width>640</width>
		<height>480</height>
		<depth>3</depth>
	</size>
	<segmented>0</segmented>
	<object>
		<name>smoke</name>
		<pose>Unspecified</pose>
		<truncated>0</truncated>
		<difficult>0</difficult>
		<occluded>0</occluded>
		<bndbox>
			<xmin>234</xmin>
			<xmax>317</xmax>
			<ymin>201</ymin>
			<ymax>250</ymax>
		</bndbox>
	</object>
</annotation>
